<?xml version="1.0"?><metadata xml:lang="en"><idinfo><native>Microsoft Windows XP Version 5.1 (Build 2600) Service Pack 3; ESRI ArcCatalog 9.3.1.1850</native><descript><abstract>The MPCA's What's in My Neighborhood contains a wide variety of environmental information about your community. This includes potentially contaminated sites, permits, licenses, registrations, inspections, and closed enforcement activities.

Potentially contaminated sites: Since the early 1980s when major federal and state cleanup programs were created, the MPCA has been aggressively searching for and helping to clean up contaminated properties, from very small to large. This website contains a searchable inventory of those properties, as well as sites that have already been cleaned up and those currently being investigated or cleaned up.

Environmental permits and registrations: This Web application also contains a searchable inventory of businesses that have applied for and received different types of environmental permits and registrations from the MPCA.

Methods for creating site locations have different levels of precision. The most accurate locations use coordinates from GPS (global positioning system). Coordinates are also derived using the site's street address, zip code or public land survey information. Some MPCA sites are not mapped. These are generally activities that are mobile, like ships with ballast water permits. 
</abstract><purpose>The data set was created as part of the Minnesota Pollution Control Agency's What's in My Neighborhood web application, which allows for public access to sites with environmental cleanup, pollution prevention,  permitted, registered, or licensed activities.</purpose><supplinf>Minnesota</supplinf></descript><citation><citeinfo><origin>Minnesota Pollution Control Agency</origin><pubdate>periodically revised</pubdate><title>What's In My Neighborhood Sites</title><geoform>vector digital data</geoform><pubinfo><publish>Minnesota Pollution Control Agency</publish></pubinfo><onlink>https://gisdata.mn.gov/dataset/env-my-neighborhood</onlink></citeinfo></citation><timeperd><current>Site locations and attributes are updated on a continual basis as new information is obtained.  Data in the distributed data files is current as of the creation date of the file.</current></timeperd><status><progress>Complete</progress><update>As needed</update></status><spdom><bounding><westbc>-97.260405</westbc><eastbc>-89.512062</eastbc><northbc>49.365608</northbc><southbc>43.436257</southbc></bounding></spdom><keywords><theme><themekey>mpca, environment, permit, registration, license, cleanup, superfund, RCRA, CERCLIS, brownfield, tank, leak, spill, NPDES, SDS, feedlot, landfill, solid waste, hazardous waste, dump, stormwater, MS4, environmental review, remediation, wastewater, toxics reduction, permit, MPCA, registration, notification, investigation, contaminated property</themekey></theme><place><placekey>minnesota</placekey></place></keywords><accconst>None</accconst><useconst>Redistribution Conditions: If you obtain data from the MPCA, it is understood that you and/or your organization have the right to use them for any purpose. If you transmit or provide these data in any form to another user, the data should be accompanied by all documentation provided with the original data set including the full metadata record.</useconst><browse><browsen>None available</browsen></browse><crossref><citeinfo><title>None</title></citeinfo></crossref><ptcontac><cntinfo><cntperp><cntorg>Minnesota Pollution Control Agency</cntorg><cntper>Sara Mueller</cntper></cntperp><cntpos>State Program Administrator</cntpos><cntaddr><addrtype>mailing and physical</addrtype><address>520 Lafayette Rd N</address><city>St. Paul</city><state>MN</state><postal>55155</postal></cntaddr><cntvoice>651-757-2593</cntvoice><cntemail>sara.mueller@state.mn.us</cntemail></cntinfo></ptcontac></idinfo><dataIdInfo><envirDesc>Microsoft Windows XP Version 5.1 (Build 2600) Service Pack 3; ESRI ArcCatalog 9.3.1.1850</envirDesc><dataLang><languageCode value="en" /></dataLang><idCitation><resTitle>wimn_sites_mpca</resTitle><presForm><PresFormCd value="005" /></presForm></idCitation><spatRpType><SpatRepTypCd value="001" /></spatRpType><dataExt><geoEle><GeoBndBox esriExtentType="native"><westBL>190220.125491</westBL><eastBL>753491.000313</eastBL><northBL>5468100.000116</northBL><southBL>4816382.000164</southBL><exTypeCode>1</exTypeCode></GeoBndBox></geoEle></dataExt><geoBox esriExtentType="decdegrees"><westBL>-97.260405</westBL><eastBL>-89.512062</eastBL><northBL>49.365608</northBL><southBL>43.436257</southBL><exTypeCode>1</exTypeCode></geoBox></dataIdInfo><metainfo><metstdn>Minnesota Geographic Metadata Guidelines</metstdn><metstdv>1.2</metstdv><mettc>local time</mettc><metd>20170323</metd><metextns><onlink>http://www.gis.state.mn.us/stds/metadata.htm</onlink><metprof>ESRI Metadata Profile</metprof></metextns><metc><cntinfo><cntperp><cntorg>Minnesota Pollution Control Agency</cntorg><cntper>Sara Mueller</cntper></cntperp><cntpos>State Program Administrator</cntpos><cntaddr><addrtype>mailing and physical</addrtype><address>520 Lafayette Rd N</address><city>St. Paul</city><state>MN</state><postal>55155</postal></cntaddr><cntvoice>651-757-2593</cntvoice><cntemail>sara.mueller@state.mn.us</cntemail></cntinfo></metc></metainfo><mdLang><languageCode value="en" /></mdLang><mdStanName>ISO 19115 Geographic Information - Metadata</mdStanName><mdStanVer>DIS_ESRI1.0</mdStanVer><mdChar><CharSetCd value="004" /></mdChar><mdHrLv><ScopeCd value="005" /></mdHrLv><mdHrLvName>dataset</mdHrLvName><distinfo><resdesc>Downloadable Data</resdesc><stdorder><digform><digtinfo><transize>8</transize><formname>Shapefile in Zip Archive</formname><formvern /></digtinfo></digform><ordering>This data can be downloaded from the Minnesota Geospatial Commons at:https://gisdata.mn.gov/dataset/env-my-neighborhood
</ordering></stdorder><distliab>Limitations: Although extensive effort has been made to produce error-free and complete data, all geographic information has limitations due to the scale, resolution, date and interpretation of the original source materials. Users should consult available data documentation (metadata) for this particular data to determine limitations and the precision to which the data depict distance, direction, location or other geographic characteristics. Data may be subject to change without prior notification.

No warranty: Data is provided "as is," without any warranty whatsoever, including but not limited to any warranty as to performance, merchantability or fitness for any particular purpose.

Liability: The entire risk as to the results of the use of this data is assumed by the user. The MPCA is not responsible for any interpretation or conclusions made by those who acquire or use it. The MPCA shall not be liable for any direct, indirect, special, incidental, compensatory or consequential damages or third-party claims resulting from the use of this data, even if the MPCA has been advised of the possibility of such potential loss or damage. In states that do not allow the exclusion or limitation of incidental or consequential damages, this data may not be used.
</distliab><distrib><cntinfo><cntperp><cntorg>Minnesota Pollution Control Agency</cntorg><cntper>Sara Mueller</cntper></cntperp><cntpos>State Program Administrator</cntpos><cntaddr><addrtype>mailing and physical</addrtype><address>520 Lafayette Rd N</address><city>St. Paul</city><state>MN</state><postal>55155</postal></cntaddr><cntvoice>651-757-2593</cntvoice><cntemail>sara.mueller@state.mn.us</cntemail></cntinfo></distrib></distinfo><distInfo><distributor><distorTran><onLineSrc><orDesc>002</orDesc><linkage>file://\\s-sp07\data\projects\wimn\wimn_sites_mpca.shp</linkage><protocol>Local Area Network</protocol></onLineSrc><transSize>2.665</transSize></distorTran><distorFormat><formatName>Shapefile</formatName></distorFormat></distributor></distInfo><spdoinfo><direct>Vector</direct><ptvctinf><sdtsterm><sdtstype>Entity point</sdtstype><ptvctcnt>99810</ptvctcnt></sdtsterm></ptvctinf><indspref>Latitude and Longitude columns contain values expressed as geographic coordinates in decimal degrees, using WGS84 as the spheroid/datum.

EPSG:4326</indspref><mgmg3obj /><mgmg3til /></spdoinfo><spref><vertdef><altsys><altenc>Explicit elevation coordinate included with horizontal coordinates</altenc><altres>1.000000</altres></altsys></vertdef><horizsys><planar><gridsys><gridsysn>Universal Transverse Mercator</gridsysn><utm><utmzone>15</utmzone></utm></gridsys><planci><plandu>meters</plandu></planci></planar><geodetic><horizdn>NAD83</horizdn><ellips>GRS80</ellips></geodetic></horizsys></spref><refSysInfo><RefSystem><refSysID><identCode>NAD_1983_UTM_Zone_15N</identCode></refSysID></RefSystem></refSysInfo><spatRepInfo><VectSpatRep><topLvl><TopoLevCd value="001" /></topLvl><geometObjs><geoObjTyp><GeoObjTypCd value="004" /></geoObjTyp><geoObjCnt>99810</geoObjCnt></geometObjs></VectSpatRep></spatRepInfo><eainfo><detailed><enttyp><enttypl>env_my_neighborhood</enttypl></enttyp><attr><attrlabl>OBJECTID</attrlabl><attrdef>Internal feature number</attrdef><attrdefs>ESRI</attrdefs><attrdomv><udom>Sequential unique whole numbers that are automatically generated. Not consistent across different versions of the data.</udom></attrdomv></attr><attr><attrlabl>SHAPE</attrlabl><attrdef>Feature geometry</attrdef><attrdefs>ESRI</attrdefs></attr><attr><attrlabl>SITE_ID</attrlabl><attrdef>The site's system ID</attrdef><attrdefs>MPCA</attrdefs></attr><attr><attrlabl>NAME</attrlabl><attrdef>The site's name</attrdef><attrdefs>MPCA</attrdefs></attr><attr><attrlabl>ACTIVE_FLAG</attrlabl><attrdef>Indicates whether site is active or not ('Y' or 'N')</attrdef><attrdefs>MPCA</attrdefs></attr><attr><attrlabl>ADDRESS_STREET</attrlabl><attrdef>Street address of physical location of site</attrdef><attrdefs>MPCA</attrdefs></attr><attr><attrlabl>ADDRESS_CITY</attrlabl><attrdef>City of physical location of site</attrdef><attrdefs>MPCA</attrdefs></attr><attr><attrlabl>ADDRESS_STATE</attrlabl><attrdef>State of physical location of site</attrdef><attrdefs>MPCA</attrdefs></attr><attr><attrlabl>ADDRESS_ZIP</attrlabl><attrdef>Zip Code of physical location of site</attrdef><attrdefs>MPCA</attrdefs></attr><attr><attrlabl>CITY</attrlabl><attrdef>City in which site is located - derived from feature location</attrdef><attrdefs>MPCA</attrdefs></attr><attr><attrlabl>COUNTY</attrlabl><attrdef>County in which site is located - derived from feature location</attrdef><attrdefs>MPCA</attrdefs></attr><attr><attrlabl>CONG_DISTRICT</attrlabl><attrdef>US Congressional district code - derived from feature location</attrdef><attrdefs>MPCA</attrdefs></attr><attr><attrlabl>SENATE_DISTRICT</attrlabl><attrdef>MN senate district - derived from feature location</attrdef><attrdefs>MPCA</attrdefs></attr><attr><attrlabl>HOUSE_DISTRICT</attrlabl><attrdef>MN house district - derived from feature location</attrdef><attrdefs>MPCA</attrdefs></attr><attr><attrlabl>HUC8</attrlabl><attrdef>USGS 8-digit watershed code - derived from feature location</attrdef><attrdefs>MPCA</attrdefs></attr><attr><attrlabl>WATERSHED_NAME</attrlabl><attrdef>Name of MN DNR major watershed associated with the USGS 8-digit watershed</attrdef><attrdefs>MPCA</attrdefs></attr><attr><attrlabl>SITE_URL</attrlabl><attrdef>URL for MPCA What's In My Neighborhood application page for this site</attrdef><attrdefs>MPCA</attrdefs></attr><attr><attrlabl>ACTIVITY</attrlabl><attrdef>MPCA activity of interest at the site</attrdef><attrdefs>MPCA</attrdefs></attr><attr><attrlabl>ACTIVITY_LIST</attrlabl><attrdef>Comma-delimited list of MPCA activities of interest at the site</attrdef><attrdefs>MPCA</attrdefs></attr><attr><attrlabl>MPCA_ID</attrlabl><attrdef>MPCA ID associated with an activity at the site</attrdef><attrdefs>MPCA</attrdefs></attr><attr><attrlabl>MPCA_ID_LIST</attrlabl><attrdef>Comma-delimited list of MPCA IDs associated with activities at the site</attrdef><attrdefs>MPCA</attrdefs></attr><attr><attrlabl>PROGRAM_CODE_LIST</attrlabl><attrdef>Comma-delimited list of codes for programs associated with activities at the site</attrdef><attrdefs>MPCA</attrdefs></attr><attr><attrlabl>PROGRAM_NAME</attrlabl><attrdef>Name of the MPCA program associated with activities at the site</attrdef><attrdefs>MPCA</attrdefs></attr><attr><attrlabl>PROGRAM_NAME_LIST</attrlabl><attrdef>Comma-delimited list of names of MPCA programs associated with activities at the site</attrdef><attrdefs>MPCA</attrdefs></attr><attr><attrlabl>INDUSTRIAL_CLASSIFICATION</attrlabl><attrdef>Primary industrial classification associated with the site</attrdef><attrdefs>MPCA</attrdefs></attr><attr><attrlabl>IC_FLAG</attrlabl><attrdef>indicates the presence of institutional controls at the site. ('Y' or 'N') These are administrative and legal controls that help minimize the potential for human exposure to contamination.</attrdef><attrdefs>MPCA</attrdefs></attr><attr><attrlabl>LATITUDE</attrlabl><attrdef>decimal degrees - coordinate y value (WGS84)</attrdef><attrdefs>MPCA</attrdefs></attr><attr><attrlabl>LONGITUDE</attrlabl><attrdef>decimal degrees - coordinate x value (WGS84)</attrdef><attrdefs>MPCA</attrdefs></attr><attr><attrlabl>COORD_COLLECT_METHOD_CODE</attrlabl><attrdef>code representing the method used to derive the location coordinates</attrdef><attrdefs>MPCA</attrdefs></attr><attr><attrlabl>COORD_COLLECT_METHOD_NAME</attrlabl><attrdef>Description of the method used to derive the location coordinates</attrdef><attrdefs>MPCA</attrdefs></attr></detailed><overview><eadetcit>None</eadetcit></overview></eainfo><mdDateSt>20090903</mdDateSt><dataqual><complete>At this time, this data set does not contain a feature for every site in the What's In My Neighborhood application.  There is an ongoing effort to improve data completeness and quality.</complete><attracc><attraccr>Attribute information comes from multiple sources, including information submitted by the site owner, information determined by MPCA staff, and information derived based on the location of the site.

The accuracy of this information has not been verified.</attraccr></attracc><logic>No known issues with logical consistency for this point data set.</logic><posacc><horizpa><horizpar>Coordinates for these features were collected using a variety of methods of varying accuracy.  The 'COORD_METH' column in the attribute table describes the method used to determine the coordinate for each feature.

A description of the coordinate collection values found in the 'COORD_METH' column can be found in the 'Attributes' section of this document.</horizpar></horizpa><vertacc><vertaccr>Not applicable.  The features in this data set do not contain Z (vertical) values.</vertaccr></vertacc></posacc><lineage><procstep><procdesc>Coordinates for these features were collected using a variety of methods of varying accuracy.  The 'COORD_METH' column in the attribute table describes the method used to determine the coordinate for each feature.

A description of the coordinate collection values found in the 'COORD_METH' column can be found in the 'Entities and Attributes' section of this document.</procdesc></procstep><srcinfo><srcscale /></srcinfo><procstep><procdesc>Metadata imported.</procdesc><srcused>D:\TestGisData\myhood\testfcs\fcForMetadata\wimn_sites_mpca.shp.xml</srcused><procdate>20090717</procdate><proctime>22333800</proctime></procstep><procstep><procdesc>Metadata imported.</procdesc><srcused>V:\projects\wimn\wimn_sites\wimn_sites_mpca.shp.xml</srcused><procdate>20090903</procdate><proctime>14043100</proctime></procstep></lineage></dataqual></metadata>